{
    "$schema": "http://json-schema.org/draft-07/schema#",
    "$id": "http://vendia.net/schemas/demos/inventory-management-system.json",
    "title": "Inventory Management System",
    "description": "Store inventory data",
    "type": "object",
    "properties": {
      "InventoryItem": {
        "description": "Inventory items",
        "type": "array",
        "items": {
          "type": "object",
          "properties": {
            "name": {
              "description": "Item name",
              "type": "string"
            },
            "sku": {
              "description": "Item number",
              "type": "string"
            },
            "quantity": {
              "description": "Available quanitity of item",
              "type": "integer"
            },
            "lastUpdated": {
              "description": "Timestamp when the item was last updated",
              "type": "string",
              "format": "date-time"
            }
          }
        }
      }
    }
  }
